molecular_dynamics_toy/__init__.py
molecular_dynamics_toy/__main__.py
molecular_dynamics_toy/app.py
molecular_dynamics_toy/calculators.py
molecular_dynamics_toy/engine.py
molecular_dynamics_toy/data/__init__.py
molecular_dynamics_toy/data/atom_properties.py
molecular_dynamics_toy/data/colors.py
molecular_dynamics_toy/data/presets.py
molecular_dynamics_toy/data/structures/CBaMnBr4.vasp
molecular_dynamics_toy/data/structures/DCA.vasp
molecular_dynamics_toy/data/structures/Eu5Sn2As6.vasp
molecular_dynamics_toy/data/structures/HAT.vasp
molecular_dynamics_toy/data/structures/PbSe_domain_wall.vasp
molecular_dynamics_toy/data/structures/__init__.py
molecular_dynamics_toy/widgets/__init__.py
molecular_dynamics_toy/widgets/base.py
molecular_dynamics_toy/widgets/controls.py
molecular_dynamics_toy/widgets/menus.py
molecular_dynamics_toy/widgets/picker.py
molecular_dynamics_toy/widgets/simulation.py
molecular_dynamics_toy-0.3.0.dist-info/licenses/LICENSE.txt
molecular_dynamics_toy-0.3.0.dist-info/METADATA
molecular_dynamics_toy-0.3.0.dist-info/WHEEL
molecular_dynamics_toy-0.3.0.dist-info/top_level.txt
molecular_dynamics_toy-0.3.0.dist-info/RECORD
