Metadata-Version: 2.4
Name: molecular_dynamics_toy
Version: 0.3.0
Summary: Interactive molecular dynamics simulation for educational purposes
Author-email: Bernard Field <bfield@lbl.gov>
Maintainer-email: Bernard Field <bfield@lbl.gov>
License-Expression: GPL-3.0-or-later
Project-URL: Repository, https://github.com/bfield1/molecular-dynamics-toy
Classifier: Development Status :: 3 - Alpha
Classifier: Intended Audience :: Education
Classifier: Intended Audience :: End Users/Desktop
Classifier: Intended Audience :: Science/Research
Classifier: Programming Language :: Python :: 3
Classifier: Topic :: Education
Classifier: Topic :: Games/Entertainment :: Simulation
Classifier: Topic :: Scientific/Engineering :: Chemistry
Classifier: Topic :: Scientific/Engineering :: Physics
Requires-Python: >=3.9
License-File: LICENSE.txt
Requires-Dist: ase
Requires-Dist: numpy
Requires-Dist: pygame
Requires-Dist: mattersim
Provides-Extra: dev
Requires-Dist: pytest; extra == "dev"
Requires-Dist: pytest-cov; extra == "dev"
Requires-Dist: pyinstaller; extra == "dev"
Requires-Dist: pip-licenses; extra == "dev"
Requires-Dist: beautifulsoup4; extra == "dev"
Dynamic: license-file
